aws_ami_delete/__init__.py
aws_ami_delete/__main__.py
aws_ami_delete-0.0.3.dist-info/LICENSE
aws_ami_delete-0.0.3.dist-info/METADATA
aws_ami_delete-0.0.3.dist-info/WHEEL
aws_ami_delete-0.0.3.dist-info/entry_points.txt
aws_ami_delete-0.0.3.dist-info/top_level.txt
aws_ami_delete-0.0.3.dist-info/RECORD
