Metadata-Version: 2.1
Name: aws-ami-delete
Version: 0.0.3
Summary: Delete AMIs - optionally from a packer manifest.
Home-page: https://github.com/lifeofguenter/aws-ami-delete
Author: Günter Grodotzki
Author-email: gunter@grodotzki.com
License: UNKNOWN
Platform: UNKNOWN
Classifier: Programming Language :: Python :: 3
Classifier: License :: OSI Approved :: MIT License
Classifier: Operating System :: OS Independent
Requires-Python: >=3
License-File: LICENSE
Requires-Dist: boto3
